tsabin/__init__.py
tsabin/meta.py
tsabin-0.1.0.dist-info/WHEEL
tsabin-0.1.0.dist-info/METADATA
tsabin-0.1.0.dist-info/RECORD
