Metadata-Version: 2.1
Name: tsabin
Version: 0.1.0
Summary: 
Author: Deepak Mallubhotla
Author-email: dmallubhotla+github@gmail.com
Requires-Python: >=3.8,<3.10
Classifier: Programming Language :: Python :: 3
Classifier: Programming Language :: Python :: 3.8
Classifier: Programming Language :: Python :: 3.9
Requires-Dist: pdme (>=0.8.7,<0.9.0)
Requires-Dist: scipy (>=1.8,<1.9)
